{"GlobalPropertiesHash":"Oikez4xQZ7NExQ8uFwHj9vx8XK/IhIgVQjjMDG4bmPo=","FingerprintPatternsHash":"gq3WsqcKBUGTSNle7RKKyXRIwh7M8ccEqOqYvIzoM04=","PropertyOverridesHash":"8ZRc1sGeVrPBx4lD717BgRaQekyh78QKV9SKsdt638U=","InputHashes":["oaH0iOXTOnGWu7\u002B7pMDTRJgMj/IgQ/L2uskHsk9P\u002BFk=","d0u\u002BaHRl2kQ5C6qMk\u002BVRZ/C\u002Brh3Ilcyia6u85chBg0k=","LFpNnDpGbZUZsMJJHs6FJpdVhRtfU1bkI5\u002BuAwu6Ixg=","2fljZZK\u002Bp5zyqKjAfKy48w9EojEoNaV91m4h41\u002BFyg0=","JVZbEA6BEIk2LC10/IP0uLSRNjhwdspU/ucTpP/3aXg="],"CachedAssets":{"oaH0iOXTOnGWu7\u002B7pMDTRJgMj/IgQ/L2uskHsk9P\u002BFk=":{"Identity":"C:\\Users\\arqua\\source\\repos\\Zoologicos\\RazorClassLibrary1\\wwwroot\\background.png","SourceId":"RazorClassLibrary1","SourceType":"Discovered","ContentRoot":"C:\\Users\\arqua\\source\\repos\\Zoologicos\\RazorClassLibrary1\\wwwroot\\","BasePath":"_content/RazorClassLibrary1","RelativePath":"background#[.{fingerprint}]?.png","AssetKind":"All","AssetMode":"All","AssetRole":"Primary","AssetMergeBehavior":null,"AssetMergeSource":"","RelatedAsset":null,"AssetTraitName":null,"AssetTraitValue":null,"Fingerprint":"x2rx4ajns0","Integrity":"WeOKCkI7IdJHs2kCqsKgLfiWX4/sNPbaRUspOLefkCY=","CopyToOutputDirectory":"Never","CopyToPublishDirectory":"PreserveNewest","OriginalItemSpec":"wwwroot\\background.png","FileLength":378,"LastWriteTime":"2026-03-24T05:43:34.5492749+00:00"},"d0u\u002BaHRl2kQ5C6qMk\u002BVRZ/C\u002Brh3Ilcyia6u85chBg0k=":{"Identity":"C:\\Users\\arqua\\source\\repos\\Zoologicos\\RazorClassLibrary1\\wwwroot\\exampleJsInterop.js","SourceId":"RazorClassLibrary1","SourceType":"Discovered","ContentRoot":"C:\\Users\\arqua\\source\\repos\\Zoologicos\\RazorClassLibrary1\\wwwroot\\","BasePath":"_content/RazorClassLibrary1","RelativePath":"exampleJsInterop#[.{fingerprint}]?.js","AssetKind":"All","AssetMode":"All","AssetRole":"Primary","AssetMergeBehavior":null,"AssetMergeSource":"","RelatedAsset":null,"AssetTraitName":null,"AssetTraitValue":null,"Fingerprint":"6pqz8bsss0","Integrity":"FrrTtczTUEHjkhc/zWRPC7CmxeXI0JCZGc1\u002B76qQ8B4=","CopyToOutputDirectory":"Never","CopyToPublishDirectory":"PreserveNewest","OriginalItemSpec":"wwwroot\\exampleJsInterop.js","FileLength":247,"LastWriteTime":"2026-03-24T05:43:34.5504512+00:00"}},"CachedCopyCandidates":{}}